sb3gen/__init__.py
sb3gen/blocks.py
sb3gen/project.py
sb3gen/py.typed
sb3gen/scratchtypes.py
sb3gen/targets.py
sb3gen-0.0.1.dist-info/METADATA
sb3gen-0.0.1.dist-info/WHEEL
sb3gen-0.0.1.dist-info/licenses/LICENSE
sb3gen-0.0.1.dist-info/RECORD
