Metadata-Version: 2.4
Name: sb3gen
Version: 0.0.1
Summary: sb3 generation library
Project-URL: Homepage, https://codeberg.org/thecoolcats/sb3gen
Project-URL: Issues, https://codeberg.org/thecoolcats/sb3genissues
Author-email: thecoolcats <thecoolcats75@proton.me>
License-Expression: BSD-3-Clause
License-File: LICENSE
Classifier: Operating System :: OS Independent
Classifier: Programming Language :: Python :: 3
Requires-Python: >=3.13
